js.bootstrap4-4.0.0-py2.7-nspkg.pth
js/bootstrap4/__init__.py
js/bootstrap4/test_bootstrap.rst
js/bootstrap4/resources/css/bootstrap-grid.css
js/bootstrap4/resources/css/bootstrap-grid.css.map
js/bootstrap4/resources/css/bootstrap-grid.min.css
js/bootstrap4/resources/css/bootstrap-grid.min.css.map
js/bootstrap4/resources/css/bootstrap-reboot.css
js/bootstrap4/resources/css/bootstrap-reboot.css.map
js/bootstrap4/resources/css/bootstrap-reboot.min.css
js/bootstrap4/resources/css/bootstrap-reboot.min.css.map
js/bootstrap4/resources/css/bootstrap.css
js/bootstrap4/resources/css/bootstrap.css.map
js/bootstrap4/resources/css/bootstrap.min.css
js/bootstrap4/resources/css/bootstrap.min.css.map
js/bootstrap4/resources/js/bootstrap.bundle.js
js/bootstrap4/resources/js/bootstrap.bundle.js.map
js/bootstrap4/resources/js/bootstrap.bundle.min.js
js/bootstrap4/resources/js/bootstrap.bundle.min.js.map
js/bootstrap4/resources/js/bootstrap.js
js/bootstrap4/resources/js/bootstrap.js.map
js/bootstrap4/resources/js/bootstrap.min.js
js/bootstrap4/resources/js/bootstrap.min.js.map
js.bootstrap4-4.0.0.dist-info/DESCRIPTION.rst
js.bootstrap4-4.0.0.dist-info/METADATA
js.bootstrap4-4.0.0.dist-info/RECORD
js.bootstrap4-4.0.0.dist-info/WHEEL
js.bootstrap4-4.0.0.dist-info/entry_points.txt
js.bootstrap4-4.0.0.dist-info/metadata.json
js.bootstrap4-4.0.0.dist-info/namespace_packages.txt
js.bootstrap4-4.0.0.dist-info/top_level.txt
