Metadata-Version: 2.0
Name: js.bootstrap4
Version: 4.0.0
Summary: fanstatic twitter bootstrap.
Home-page: https://github.com/gocept/js.bootstrap4
Author: gocept developers
Author-email: mail@gocept.com
License: BSD
Keywords: fanstatic twitter bootstrap
Platform: UNKNOWN
Classifier: Development Status :: 5 - Production/Stable
Classifier: Environment :: Web Environment
Classifier: Intended Audience :: Developers
Classifier: License :: OSI Approved :: BSD License
Classifier: Operating System :: OS Independent
Classifier: Programming Language :: JavaScript
Classifier: Programming Language :: Python :: 2.7
Classifier: Programming Language :: Python :: 3.4
Classifier: Programming Language :: Python :: 3.5
Classifier: Programming Language :: Python :: 3.6
Classifier: Programming Language :: Python :: 3.7
Classifier: Programming Language :: Python :: Implementation :: CPython
Classifier: Programming Language :: Zope
Classifier: Topic :: Internet :: WWW/HTTP :: Dynamic Content
Classifier: Topic :: Software Development :: Libraries :: Application Frameworks
Classifier: Topic :: Software Development :: User Interfaces
Classifier: Topic :: Software Development :: Widget Sets
Requires-Dist: fanstatic (>=1.0a3)
Requires-Dist: js.jquery (>=1.9.1)
Requires-Dist: setuptools
